thermopro_tp25_ble/__init__.py
thermopro_tp25_ble/client.py
thermopro_tp25_ble/constants.py
thermopro_tp25_ble-0.1.1.dist-info/licenses/LICENSE
thermopro_tp25_ble-0.1.1.dist-info/METADATA
thermopro_tp25_ble-0.1.1.dist-info/WHEEL
thermopro_tp25_ble-0.1.1.dist-info/top_level.txt
thermopro_tp25_ble-0.1.1.dist-info/RECORD
