Metadata-Version: 2.4
Name: thermopro-tp25-ble
Version: 0.1.1
Summary: Thermopro TP25 BLE Library
Author: kwood1992
License-Expression: Apache-2.0
Project-URL: Homepage, https://github.com/kwood1992/thermopro-tp25-ble
Project-URL: Changelog, https://github.com/kwood1992/thermopro-tp25-ble/releases
Project-URL: Issues, https://github.com/kwood1992/thermopro-tp25-ble/issues
Project-URL: CI, https://github.com/kwood1992/thermopro-tp25-ble/actions
Requires-Python: >=3.10
License-File: LICENSE
Requires-Dist: bleak>=1.0.1
Provides-Extra: test
Requires-Dist: pytest; extra == "test"
Dynamic: license-file
